AUTHORS
CHANGELOG.md
CONTRIBUTING.md
LICENSE.txt
MAINTAINERS.md
MANIFEST.in
README.md
setup.py
bin/hemlock
docs/CLI.md
docs/images/logo.png
docs/images/overview_hemlock.png
hemlock/__init__.py
hemlock/hemlock.py
hemlock/hemlock_creds_sample
hemlock/hemlock_creds_source_sample
hemlock/hemlock_options_parser.py
hemlock/test_hemlock.py
hemlock.egg-info/PKG-INFO
hemlock.egg-info/SOURCES.txt
hemlock.egg-info/dependency_links.txt
hemlock.egg-info/requires.txt
hemlock.egg-info/top_level.txt
hemlock/clients/README.md
hemlock/clients/__init__.py
hemlock/clients/fs_creds_sample
hemlock/clients/hemlock_base.py
hemlock/clients/hfs.py
hemlock/clients/hmongo.py
hemlock/clients/hmysql.py
hemlock/clients/hredis.py
hemlock/clients/hrest.py
hemlock/clients/hstream_odd.py
hemlock/clients/mongo_creds_sample
hemlock/clients/mysql_creds_sample
hemlock/clients/redis_creds_sample
hemlock/clients/rest_creds_sample
hemlock/clients/stream_odd_creds_sample
hemlock/clients/test_hemlock_base.py
hemlock/clients/test_hfs.py
hemlock/clients/test_hmongo.py
hemlock/clients/test_hmysql.py
hemlock/clients/test_hredis.py
hemlock/clients/test_hrest.py
hemlock/load_scripts/__init__.py
hemlock/load_scripts/csv_to_mysql.py
hemlock/load_scripts/csv_to_redis_hash.py
hemlock/load_scripts/doc_to_mongo.py
scripts/ci/setup_env_hemlock.sh