Metadata-Version: 1.1
Name: hemlock
Version: 0.1.0
Summary: Hemlock is a way of providing a common data access layer.
Home-page: http://lab41.github.io/Hemlock
Author: Charlie Lewis
Author-email: charliel@lab41.org
License: LICENSE.txt
Keywords: hemlock,metadata,cache,heterogeneous
Platform: UNKNOWN
Classifier: Programming Language :: Python
Classifier: Operating System :: POSIX :: Linux
Classifier: Topic :: Software Development :: Libraries :: Application Frameworks
Classifier: Environment :: Other Environment
